app/__init__.py
app/main.py
app/sections/__init__.py
app/sections/data_exploration.py
app/sections/model_evaluation.py
app/sections/model_training.py
garbage_classifier-1.0.0.dist-info/licenses/LICENSE
source/__init__.py
source/predict.py
source/train.py
source/utils/__init__.py
source/utils/carbon_utils.py
source/utils/config.py
source/utils/custom_classes/EdaAnalyzer.py
source/utils/custom_classes/EvalAnalyzer.py
source/utils/custom_classes/GarbageClassifier.py
source/utils/custom_classes/GarbageDataModule.py
source/utils/custom_classes/LossCurveCallback.py
source/utils/custom_classes/__init__.py
garbage_classifier-1.0.0.dist-info/METADATA
garbage_classifier-1.0.0.dist-info/WHEEL
garbage_classifier-1.0.0.dist-info/entry_points.txt
garbage_classifier-1.0.0.dist-info/top_level.txt
garbage_classifier-1.0.0.dist-info/RECORD
