Metadata-Version: 2.4
Name: garbage_classifier
Version: 1.0.0
Summary: Finetunned ResNet18 for garbage image classification
Author: Melchor Lafuente, Iker Jauregui
Maintainer: Melchor Lafuente, Iker Jauregui
Keywords: machine-learning,datascience,ai,garbage,garbage classifier,garbage-classifier,garbage_classifier,resnet
Requires-Python: <3.12,>=3.11
License-File: LICENSE
Requires-Dist: lightning>=2.5.2
Requires-Dist: matplotlib>=3.10.6
Requires-Dist: numba>=0.61.2
Requires-Dist: numpy<2
Requires-Dist: pandas>=2.3.2
Requires-Dist: pyarrow>=21.0.0
Requires-Dist: seaborn>=0.13.2
Requires-Dist: tables>=3.10.2
Requires-Dist: tensorboard>=2.18.0
Requires-Dist: tensorflow==2.18.*
Requires-Dist: torch>=2.7.1
Requires-Dist: torchinfo>=1.8.0
Requires-Dist: torchvision>=0.22.1
Requires-Dist: scikit-learn
Requires-Dist: gdown
Requires-Dist: gradio>=5.49.1
Requires-Dist: codecarbon>=3.0.7
Requires-Dist: opencv-python>=4.11.0.86
Requires-Dist: requests>=2.31.0
Requires-Dist: tqdm>=4.66.0
Dynamic: license-file
